{
  "apiVersion":"cloudplus.io/v1alpha3",
  "kind":"VirtualMachineTemplate",
  "metadata":{
    "additionalProperties":{},
    "finalizers":[],
    "managedFields":[],
    "name":"virtualmachine-insertiso",
    "ownerReferences":[]
  },
  "spec":{
    "data":{
      "lifecycle":{
        "insertISO":{
          "path":"String",
          "current":true,
          "insert":true,
          "block":true,
          "force":true,
          "config":true,
          "live":true
        }
      },
      "additionalProperties":{}
    },
    "type":"VirtualMachine"
  }
}
